pyblur/BoxBlur.py
pyblur/DefocusBlur.py
pyblur/GaussianBlur.py
pyblur/LineDictionary.py
pyblur/LinearMotionBlur.py
pyblur/PsfBlur.py
pyblur/RandomizedBlur.py
pyblur/__init__.py
pyblur/psf.pkl
pyblur-0.2.3.dist-info/DESCRIPTION.rst
pyblur-0.2.3.dist-info/METADATA
pyblur-0.2.3.dist-info/RECORD
pyblur-0.2.3.dist-info/WHEEL
pyblur-0.2.3.dist-info/metadata.json
pyblur-0.2.3.dist-info/top_level.txt
