Metadata-Version: 2.0
Name: pyblur
Version: 0.2.3
Summary: Image blurring routines
Home-page: http://github.com/lospooky/pyblur
Author: lospooky
Author-email: my.accounts@gmx.se
License: MIT
Keywords: blur
Platform: UNKNOWN
Classifier: Development Status :: 3 - Alpha
Classifier: License :: OSI Approved :: MIT License
Classifier: Intended Audience :: Developers
Classifier: Intended Audience :: Science/Research
Classifier: Programming Language :: Python :: 2.7
Classifier: Topic :: Multimedia :: Graphics
Requires-Dist: numpy
Requires-Dist: pillow
Requires-Dist: scikit-image
Requires-Dist: scipy
